setup.cfg
setup.py
jpack/__init__.py
jpack/cal.py
jpack.egg-info/PKG-INFO
jpack.egg-info/SOURCES.txt
jpack.egg-info/dependency_links.txt
jpack.egg-info/top_level.txt