Metadata-Version: 1.0
Name: jpack
Version: 0.0.1
Summary: this is a trial package used for learning.
Home-page: UNKNOWN
Author: Jayashree M Kudari
Author-email: mk.jayashree@jainuniversity.ac.in
License: MIT
Platform: UNKNOWN
